gbpservice/__init__.py
gbpservice/common/__init__.py
gbpservice/common/utils.py
gbpservice/contrib/__init__.py
gbpservice/contrib/nfp/__init__.py
gbpservice/contrib/nfp/bin/nfp.ini
gbpservice/contrib/nfp/bin/nfp_controller.ini
gbpservice/contrib/nfp/bin/policy.json
gbpservice/contrib/nfp/config_orchestrator/__init__.py
gbpservice/contrib/nfp/config_orchestrator/common/__init__.py
gbpservice/contrib/nfp/config_orchestrator/common/common.py
gbpservice/contrib/nfp/config_orchestrator/common/lbv2_constants.py
gbpservice/contrib/nfp/config_orchestrator/common/topics.py
gbpservice/contrib/nfp/config_orchestrator/handlers/__init__.py
gbpservice/contrib/nfp/config_orchestrator/handlers/config/__init__.py
gbpservice/contrib/nfp/config_orchestrator/handlers/config/firewall.py
gbpservice/contrib/nfp/config_orchestrator/handlers/config/loadbalancer.py
gbpservice/contrib/nfp/config_orchestrator/handlers/config/loadbalancerv2.py
gbpservice/contrib/nfp/config_orchestrator/handlers/config/vpn.py
gbpservice/contrib/nfp/config_orchestrator/handlers/notification/__init__.py
gbpservice/contrib/nfp/config_orchestrator/handlers/notification/handler.py
gbpservice/contrib/nfp/config_orchestrator/modules/__init__.py
gbpservice/contrib/nfp/config_orchestrator/modules/config_orch.py
gbpservice/contrib/nfp/configurator/__init__.py
gbpservice/contrib/nfp/configurator/advanced_controller/__init__.py
gbpservice/contrib/nfp/configurator/advanced_controller/controller.py
gbpservice/contrib/nfp/configurator/advanced_controller/controller_loader.py
gbpservice/contrib/nfp/configurator/agents/__init__.py
gbpservice/contrib/nfp/configurator/agents/agent_base.py
gbpservice/contrib/nfp/configurator/agents/firewall.py
gbpservice/contrib/nfp/configurator/agents/generic_config.py
gbpservice/contrib/nfp/configurator/agents/loadbalancer_v1.py
gbpservice/contrib/nfp/configurator/agents/loadbalancer_v2.py
gbpservice/contrib/nfp/configurator/agents/nfp_service.py
group_based_policy-2015.2.8.dist-info/DESCRIPTION.rst
group_based_policy-2015.2.8.dist-info/METADATA
group_based_policy-2015.2.8.dist-info/RECORD
group_based_policy-2015.2.8.dist-info/WHEEL
group_based_policy-2015.2.8.dist-info/entry_points.txt
group_based_policy-2015.2.8.dist-info/metadata.json
group_based_policy-2015.2.8.dist-info/pbr.json
group_based_policy-2015.2.8.dist-info/top_level.txt
